musical_mel_transform/__init__.py
musical_mel_transform/conv_fft.py
musical_mel_transform/musical_mel.py
musical_mel_transform/scripts/__init__.py
musical_mel_transform/scripts/benchmark_performance.py
musical_mel_transform/scripts/compare_feats.py
musical_mel_transform/scripts/demo.py
musical_mel_transform-0.1.1.dist-info/METADATA
musical_mel_transform-0.1.1.dist-info/WHEEL
musical_mel_transform-0.1.1.dist-info/entry_points.txt
musical_mel_transform-0.1.1.dist-info/licenses/LICENSE
musical_mel_transform-0.1.1.dist-info/RECORD
