Metadata-Version: 2.4
Name: musical-mel-transform
Version: 0.1.1
Summary: A PyTorch-based musical mel-frequency transform for audio processing
Project-URL: Homepage, https://github.com/worldveil/musical_mel_transform_torch
Project-URL: Repository, https://github.com/worldveil/musical_mel_transform_torch.git
Project-URL: Issues, https://github.com/worldveil/musical_mel_transform_torch/issues
Author-email: Your Name <your.email@example.com>
License: MIT License
License-File: LICENSE
Keywords: audio,mel,music,pytorch,signal-processing,transform
Classifier: Development Status :: 4 - Beta
Classifier: Intended Audience :: Developers
Classifier: Intended Audience :: Science/Research
Classifier: License :: OSI Approved :: MIT License
Classifier: Operating System :: OS Independent
Classifier: Programming Language :: Python :: 3
Classifier: Programming Language :: Python :: 3.8
Classifier: Programming Language :: Python :: 3.9
Classifier: Programming Language :: Python :: 3.10
Classifier: Programming Language :: Python :: 3.11
Classifier: Programming Language :: Python :: 3.12
Classifier: Topic :: Multimedia :: Sound/Audio :: Analysis
Classifier: Topic :: Scientific/Engineering :: Artificial Intelligence
Requires-Python: >=3.8
Requires-Dist: black>=23.0.0
Requires-Dist: flake8>=5.0.0
Requires-Dist: ipython>=8.12.3
Requires-Dist: isort>=5.0.0
Requires-Dist: librosa>=0.9.0
Requires-Dist: matplotlib>=3.7.5
Requires-Dist: mypy>=1.0.0
Requires-Dist: numpy>=1.21.0
Requires-Dist: onnx>=1.16.0
Requires-Dist: onnxruntime>=1.17.0
Requires-Dist: onnxscript>=0.1.0.dev20240617
Requires-Dist: pre-commit>=3.0.0
Requires-Dist: pytest-cov>=4.0.0
Requires-Dist: pytest>=7.0.0
Requires-Dist: scipy>=1.7.0
Requires-Dist: seaborn>=0.11.0
Requires-Dist: sphinx-rtd-theme>=1.0.0
Requires-Dist: sphinx>=5.0.0
Requires-Dist: torch>=2.1.0
Requires-Dist: torchaudio>=2.1.0
Requires-Dist: tqdm>=4.64.0
